{"Chile":{"Chile":{"customDictionary":{"count":1,"lastUpdated":1684545873244}}},"Norte Grande":{"Norte Grande":{"internalLink":{"count":1,"lastUpdated":1684545881498}}},"Norte Semiárido":{"Norte Semiárido":{"internalLink":{"count":1,"lastUpdated":1684545886183}}},"Authorities":{"Authorities":{"customDictionary":{"count":1,"lastUpdated":1684546261371}}},"setup":{"setup":{"frontMatter":{"count":2,"lastUpdated":1684549987739}}},"Formativo Medio":{"Formativo Medio":{"internalLink":{"count":1,"lastUpdated":1684554047198}}},"Formativo Tardío":{"Formativo Tardío":{"internalLink":{"count":1,"lastUpdated":1684554058623}}},"Loa Bajo":{"Loa Bajo":{"internalLink":{"count":1,"lastUpdated":1684554113564}}},"Loa Medio":{"Loa Medio":{"internalLink":{"count":1,"lastUpdated":1684554117812}}},"buscador":{"buscador":{"customDictionary":{"count":1,"lastUpdated":1684555445860}}},"abajo":{"abajo":{"customDictionary":{"count":1,"lastUpdated":1684555458033}}},"Fasces":{"Fasces":{"customDictionary":{"count":1,"lastUpdated":1684555508597}}},"Fase Azapa":{"Fase Azapa":{"internalLink":{"count":1,"lastUpdated":1684555526401}}},"Fase Faldas del Morro":{"Fase Faldas del Morro":{"internalLink":{"count":1,"lastUpdated":1684555753508}}},"Importancia":{"Importancia":{"customDictionary":{"count":1,"lastUpdated":1684555956743}}},"Periodos":{"Periodos":{"currentFile":{"count":1,"lastUpdated":1684556825573}}},"Subregiones":{"Subregiones":{"currentFile":{"count":1,"lastUpdated":1684622649894}}},"histórico":{"histórico":{"customDictionary":{"count":1,"lastUpdated":1684717176947}}},"Periodo Alfarero Temprano (0-800 dC)":{"Periodo Alfarero Temprano (0-800 dC)":{"internalLink":{"count":1,"lastUpdated":1684717288694}}},"investigacion":{"investigación":{"customDictionary":{"count":1,"lastUpdated":1684717351191}}},"decada":{"década":{"customDictionary":{"count":1,"lastUpdated":1684717363568}}},"Materialidad":{"Materialidad":{"customDictionary":{"count":1,"lastUpdated":1684717410801}}},"Viviendas":{"Viviendas":{"internalLink":{"count":1,"lastUpdated":1684718323038}}},"ocupación":{"ocupación":{"customDictionary":{"count":1,"lastUpdated":1684718414124}}}}